arena/__init__.py
arena/__main__.py
arena/arena_mqtt.py
arena/auth.py
arena/base_object.py
arena/device.py
arena/env.py
arena/scene.py
arena/topics.py
arena/attributes/__init__.py
arena/attributes/animation.py
arena/attributes/animation_mixer.py
arena/attributes/armarker.py
arena/attributes/attribute.py
arena/attributes/attribution.py
arena/attributes/blip.py
arena/attributes/box_collision_listener.py
arena/attributes/click_listener.py
arena/attributes/color.py
arena/attributes/data.py
arena/attributes/data_event.py
arena/attributes/dynamic_body.py
arena/attributes/gltf_model_lod.py
arena/attributes/gltf_morph.py
arena/attributes/goto_landmark.py
arena/attributes/goto_url.py
arena/attributes/impulse.py
arena/attributes/jitsi_video.py
arena/attributes/landmark.py
arena/attributes/material.py
arena/attributes/material_extras.py
arena/attributes/model_container.py
arena/attributes/model_update.py
arena/attributes/multisrc.py
arena/attributes/physx_body.py
arena/attributes/physx_force_pushable.py
arena/attributes/physx_joint.py
arena/attributes/physx_joint_constraint.py
arena/attributes/physx_joint_driver.py
arena/attributes/physx_material.py
arena/attributes/position.py
arena/attributes/remote_render.py
arena/attributes/rotation.py
arena/attributes/scale.py
arena/attributes/shadow.py
arena/attributes/sound.py
arena/attributes/spe_particles.py
arena/attributes/static_body.py
arena/attributes/textinput.py
arena/attributes/translate.py
arena/attributes/video_control.py
arena/chat/__init__.py
arena/chat/chat.py
arena/event_loop/__init__.py
arena/event_loop/async_worker.py
arena/event_loop/asyncio_mqtt.py
arena/event_loop/event_loop.py
arena/event_loop/lazy_worker.py
arena/event_loop/persistent_worker.py
arena/event_loop/single_worker.py
arena/event_loop/worker.py
arena/events/__init__.py
arena/events/event.py
arena/objects/__init__.py
arena/objects/arena_object.py
arena/objects/arenaui_button_panel.py
arena/objects/arenaui_card.py
arena/objects/arenaui_prompt.py
arena_py-1.4.0.dist-info/licenses/LICENSE
arena_py-1.4.0.dist-info/METADATA
arena_py-1.4.0.dist-info/WHEEL
arena_py-1.4.0.dist-info/entry_points.txt
arena_py-1.4.0.dist-info/top_level.txt
arena_py-1.4.0.dist-info/RECORD
