Metadata-Version: 2.4
Name: arena-py
Version: 1.4.0
Summary: Draw objects and run programs in the ARENA using Python!
Home-page: https://github.com/arenaxr/arena-py
Author: Carnegie Mellon University
Author-email: arenaxr@andrew.cmu.edu
License: BSD 3-clause "New" or "Revised License"
Classifier: Programming Language :: Python :: 3
Classifier: Operating System :: OS Independent
Requires-Python: >=3.10
License-File: LICENSE
Requires-Dist: paho-mqtt~=2.1.0
Requires-Dist: opentelemetry-exporter-otlp-proto-grpc==1.21.*
Dynamic: author
Dynamic: author-email
Dynamic: classifier
Dynamic: description
Dynamic: description-content-type
Dynamic: home-page
Dynamic: license
Dynamic: license-file
Dynamic: requires-dist
Dynamic: requires-python
Dynamic: summary
